CHANGES
LICENSE
MANIFEST.in
README.rst
setup.py
undrp/__init__.py
undrp/drp.py
undrp/io.py
undrp/main.py
undrp/pdf.py
undrp.egg-info/PKG-INFO
undrp.egg-info/SOURCES.txt
undrp.egg-info/dependency_links.txt
undrp.egg-info/entry_points.txt
undrp.egg-info/requires.txt
undrp.egg-info/top_level.txt