Metadata-Version: 1.1
Name: undrp
Version: 0.2.0
Summary: Convert DRP-formatted Barnes & Noble e-books to a portable format
Home-page: https://github.com/avoidscorn/undrp
Author: Conor Davis
Author-email: undrp@conor.fastmail.fm
License: MIT
Keywords: bnfixedformat convert drp epub pdf
Platform: UNKNOWN
Classifier: Development Status :: 3 - Alpha
Classifier: Environment :: Console
Classifier: Intended Audience :: End Users/Desktop
Classifier: License :: OSI Approved :: MIT License
Classifier: Operating System :: OS Independent
Classifier: Programming Language :: Python :: 3.3
Classifier: Programming Language :: Python :: 3.4
Classifier: Programming Language :: Python :: Implementation :: CPython
Classifier: Topic :: Multimedia :: Graphics :: Graphics Conversion
